{
  "user": {
    "contributionsCollection": {
      "contributionCalendar": {
        "totalContributions": 85,
        "weeks": [
          {
            "contributionDays": [
              {
                "contributionCount": 1,
                "date": "2026-01-01"
              },
              {
                "contributionCount": 1,
                "date": "2026-01-02"
              },
              {
                "contributionCount": 1,
                "date": "2026-01-03"
              }
            ]
          },
          {
            "contributionDays": [
              {
                "contributionCount": 2,
                "date": "2026-01-04"
              },
              {
                "contributionCount": 7,
                "date": "2026-01-05"
              },
              {
                "contributionCount": 5,
                "date": "2026-01-06"
              },
              {
                "contributionCount": 10,
                "date": "2026-01-07"
              },
              {
                "contributionCount": 2,
                "date": "2026-01-08"
              },
              {
                "contributionCount": 2,
                "date": "2026-01-09"
              },
              {
                "contributionCount": 1,
                "date": "2026-01-10"
              }
            ]
          },
          {
            "contributionDays": [
              {
                "contributionCount": 3,
                "date": "2026-01-11"
              },
              {
                "contributionCount": 6,
                "date": "2026-01-12"
              },
              {
                "contributionCount": 5,
                "date": "2026-01-13"
              },
              {
                "contributionCount": 2,
                "date": "2026-01-14"
              },
              {
                "contributionCount": 5,
                "date": "2026-01-15"
              },
              {
                "contributionCount": 0,
                "date": "2026-01-16"
              },
              {
                "contributionCount": 1,
                "date": "2026-01-17"
              }
            ]
          },
          {
            "contributionDays": [
              {
                "contributionCount": 5,
                "date": "2026-01-18"
              },
              {
                "contributionCount": 2,
                "date": "2026-01-19"
              },
              {
                "contributionCount": 1,
                "date": "2026-01-20"
              },
              {
                "contributionCount": 6,
                "date": "2026-01-21"
              },
              {
                "contributionCount": 7,
                "date": "2026-01-22"
              },
              {
                "contributionCount": 10,
                "date": "2026-01-23"
              },
              {
                "contributionCount": 0,
                "date": "2026-01-24"
              }
            ]
          }
        ]
      }
    }
  }
}
